insight_extractor/__init__.py
insight_extractor/pipeline.py
insight_extractor/predict.py
insight_extractor/preprocessors.py
insight_extractor/tests/__init__.py
insight_extractor/tests/test_insight_extractor.py
insight_extractor-0.1.1.dist-info/LICENSE
insight_extractor-0.1.1.dist-info/METADATA
insight_extractor-0.1.1.dist-info/WHEEL
insight_extractor-0.1.1.dist-info/top_level.txt
insight_extractor-0.1.1.dist-info/RECORD
