Metadata-Version: 2.1
Name: insight-extractor
Version: 0.1.1
Summary: Identify Insights in Full Text Documents
Home-page: https://github.com/NoahFinberg/insight_extractor
Author: Noah Finberg
Author-email: noahfinberg@gmail.com
License: MIT
Platform: UNKNOWN
Classifier: License :: OSI Approved :: MIT License
Classifier: Programming Language :: Python
Classifier: Programming Language :: Python :: 3
Classifier: Programming Language :: Python :: 3.6
Classifier: Programming Language :: Python :: Implementation :: CPython
Classifier: Programming Language :: Python :: Implementation :: PyPy
Requires-Python: >=3.6.0
Requires-Dist: absl-py (==0.11.0)
Requires-Dist: alabaster (==0.7.12)
Requires-Dist: astunparse (==1.6.3)
Requires-Dist: atomicwrites (==1.4.0)
Requires-Dist: attrs (==20.3.0)
Requires-Dist: Babel (==2.9.0)
Requires-Dist: bleach (==3.2.1)
Requires-Dist: cachetools (==4.2.0)
Requires-Dist: certifi (==2020.12.5)
Requires-Dist: chardet (==4.0.0)
Requires-Dist: click (==7.1.2)
Requires-Dist: colorama (==0.4.4)
Requires-Dist: docutils (==0.16)
Requires-Dist: flatbuffers (==1.12)
Requires-Dist: gast (==0.3.3)
Requires-Dist: google-auth (==1.24.0)
Requires-Dist: google-auth-oauthlib (==0.4.2)
Requires-Dist: google-pasta (==0.2.0)
Requires-Dist: grpcio (==1.32.0)
Requires-Dist: h5py (==2.10.0)
Requires-Dist: idna (==2.10)
Requires-Dist: imagesize (==1.2.0)
Requires-Dist: importlib-metadata (==3.4.0)
Requires-Dist: iniconfig (==1.1.1)
Requires-Dist: Jinja2 (==2.11.2)
Requires-Dist: joblib (==1.0.0)
Requires-Dist: Keras-Preprocessing (==1.1.2)
Requires-Dist: keyring (==21.8.0)
Requires-Dist: Markdown (==3.3.3)
Requires-Dist: MarkupSafe (==1.1.1)
Requires-Dist: more-itertools (==8.6.0)
Requires-Dist: nltk (==3.5)
Requires-Dist: numpy (==1.19.5)
Requires-Dist: oauthlib (==3.1.0)
Requires-Dist: opt-einsum (==3.3.0)
Requires-Dist: packaging (==20.8)
Requires-Dist: pandas (==1.1.5)
Requires-Dist: pathlib (==1.0.1)
Requires-Dist: pkginfo (==1.6.1)
Requires-Dist: pluggy (==0.13.1)
Requires-Dist: protobuf (==3.14.0)
Requires-Dist: py (==1.10.0)
Requires-Dist: pyasn1 (==0.4.8)
Requires-Dist: pyasn1-modules (==0.2.8)
Requires-Dist: Pygments (==2.7.4)
Requires-Dist: pyparsing (==2.4.7)
Requires-Dist: pytest (==6.2.1)
Requires-Dist: python-dateutil (==2.8.1)
Requires-Dist: pytz (==2020.5)
Requires-Dist: readme-renderer (==28.0)
Requires-Dist: regex (==2020.11.13)
Requires-Dist: requests (==2.25.1)
Requires-Dist: requests-oauthlib (==1.3.0)
Requires-Dist: requests-toolbelt (==0.9.1)
Requires-Dist: rfc3986 (==1.4.0)
Requires-Dist: rsa (==4.7)
Requires-Dist: scikit-learn (==0.24.0)
Requires-Dist: scipy (==1.5.4)
Requires-Dist: six (==1.15.0)
Requires-Dist: sklearn (==0.0)
Requires-Dist: snowballstemmer (==2.0.0)
Requires-Dist: Sphinx (==3.4.3)
Requires-Dist: sphinxcontrib-applehelp (==1.0.2)
Requires-Dist: sphinxcontrib-devhelp (==1.0.2)
Requires-Dist: sphinxcontrib-htmlhelp (==1.0.3)
Requires-Dist: sphinxcontrib-jsmath (==1.0.1)
Requires-Dist: sphinxcontrib-qthelp (==1.0.3)
Requires-Dist: sphinxcontrib-serializinghtml (==1.1.4)
Requires-Dist: tensorboard (==2.4.1)
Requires-Dist: tensorboard-plugin-wit (==1.7.0)
Requires-Dist: tensorflow (==2.4.0)
Requires-Dist: tensorflow-estimator (==2.4.0)
Requires-Dist: termcolor (==1.1.0)
Requires-Dist: threadpoolctl (==2.1.0)
Requires-Dist: toml (==0.10.2)
Requires-Dist: tqdm (==4.56.0)
Requires-Dist: twine (==3.3.0)
Requires-Dist: typing-extensions (==3.7.4.3)
Requires-Dist: urllib3 (==1.26.2)
Requires-Dist: wcwidth (==0.2.5)
Requires-Dist: webencodings (==0.5.1)
Requires-Dist: Werkzeug (==1.0.1)
Requires-Dist: wrapt (==1.12.1)
Requires-Dist: zipp (==3.4.0)
